libpve/__init__.py
libpve/http.py
libpve/shell.py
libpve-0.2.0.dist-info/DESCRIPTION.rst
libpve-0.2.0.dist-info/METADATA
libpve-0.2.0.dist-info/RECORD
libpve-0.2.0.dist-info/WHEEL
libpve-0.2.0.dist-info/metadata.json
libpve-0.2.0.dist-info/top_level.txt
