Metadata-Version: 2.0
Name: libpve
Version: 0.2.0
Summary: Python interface for interacting with proxmox.
Home-page: https://github.com/m-o-n-k/python.libpve.git
Author: Thomas Steinert
Author-email: monk@10forge.org
License: GPLv3
Keywords: api,http,proxmox,pve,shell
Platform: UNKNOWN
Classifier: Topic :: Software Development :: Libraries
Classifier: Topic :: System :: Systems Administration
Classifier: Programming Language :: Python :: 3.5
Requires-Dist: paramiko (>=1.16.0)
